tamer/__init__.py
tamer/core.py
async_tamer-1.0.0.dist-info/LICENSE
async_tamer-1.0.0.dist-info/METADATA
async_tamer-1.0.0.dist-info/WHEEL
async_tamer-1.0.0.dist-info/RECORD
