Metadata-Version: 2.1
Name: async-tamer
Version: 1.0.0
Summary: Python library for writing asynchronous programs.
License: BSD 3-clause
Author: Sebastian Wallkötter
Author-email: sebastian@wallkoetter.net
Requires-Python: >=3.10,<4.0
Classifier: License :: Other/Proprietary License
Classifier: Programming Language :: Python :: 3
Classifier: Programming Language :: Python :: 3.10
Classifier: Programming Language :: Python :: 3.11
Classifier: Programming Language :: Python :: 3.12
